brownie_tokens/__init__.py
brownie_tokens/forked.py
brownie_tokens/template.py
brownie_tokens/token-template.vy
brownie_token_tester-0.3.2.dist-info/LICENSE
brownie_token_tester-0.3.2.dist-info/METADATA
brownie_token_tester-0.3.2.dist-info/WHEEL
brownie_token_tester-0.3.2.dist-info/top_level.txt
brownie_token_tester-0.3.2.dist-info/RECORD
