Metadata-Version: 2.1
Name: brownie-token-tester
Version: 0.3.2
Summary: Helper objects for generating ERC20s while testing a Brownie project.
Home-page: https://github.com/iamdefinitelyahuman/brownie-token-tester
Author: Ben Hauser
Author-email: ben@hauser.id
License: MIT
Keywords: brownie,ethereum,web3py
Platform: UNKNOWN
Classifier: Development Status :: 5 - Production/Stable
Classifier: Intended Audience :: Developers
Classifier: Topic :: Software Development :: Build Tools
Classifier: License :: OSI Approved :: MIT License
Classifier: Programming Language :: Python :: 3
Classifier: Programming Language :: Python :: 3.6
Classifier: Programming Language :: Python :: 3.7
Classifier: Programming Language :: Python :: 3.8
Classifier: Programming Language :: Python :: 3.9
Requires-Python: >=3.6,<4
Requires-Dist: eth-brownie (<2.0.0,>=1.11.6)
